django_user_role/__init__.py
django_user_role/admin.py
django_user_role/apps.py
django_user_role/checkers.py
django_user_role/decorators.py
django_user_role/exceptions.py
django_user_role/loader.py
django_user_role/models.py
django_user_role/permissions.py
django_user_role/role.py
django_user_role/utils.py
django_user_role-0.0.1.dist-info/LICENSE
django_user_role-0.0.1.dist-info/METADATA
django_user_role-0.0.1.dist-info/WHEEL
django_user_role-0.0.1.dist-info/top_level.txt
django_user_role-0.0.1.dist-info/RECORD
